[
  {
    "id": "cliente-1",
    "nombre": "Cliente Inicial 1",
    "nro_documento": "111",
    "nro_movil": "3001111111",
    "correo": "cliente1@test.com",
    "tipo_cliente": "Persona Natural",
    "tipo_identificacion": "CC",
    "situacion": "Activo",
    "nro_correlativo": 1
  },
  {
    "id": "cliente-2",
    "nombre": "Cliente Inicial 2",
    "nro_documento": "222",
    "nro_movil": "3002222222",
    "correo": "cliente2@test.com",
    "tipo_cliente": "Persona Natural",
    "tipo_identificacion": "CC",
    "situacion": "Activo",
    "nro_correlativo": 2
  },
  {
    "id": "66af58e0-08ea-4549-90e5-3d742bcaa303",
    "nro_correlativo": 3,
    "fecha_creacion": "2026-05-28T02:17:19.111Z",
    "situacion": "Activo",
    "tipo_cliente": "Persona Natural",
    "tipo_identificacion": "CC",
    "nombre": "CLIENTE_PRUEBA_1",
    "nro_documento": "123456",
    "correo": "prueba1@test.com",
    "nro_movil": "3001234567"
  },
  {
    "id": "16547ff6-f691-4e93-8a42-d5ca9f78852b",
    "nro_correlativo": 4,
    "fecha_creacion": "2026-05-28T02:17:29.244Z",
    "situacion": "Activo",
    "tipo_cliente": "Persona Natural",
    "tipo_identificacion": "CC",
    "nombre": "CLIENTE_PRUEBA_2",
    "nro_documento": "789012",
    "correo": "prueba2@test.com",
    "nro_movil": "3009876543"
  }
]